LICENSE.txt
MANIFEST.in
README.md
setup.py
weighted_bootstrap_randomforest/__init__.py
weighted_bootstrap_randomforest/weighted_bootstrap_randomforest.py
weighted_bootstrap_randomforest.egg-info/PKG-INFO
weighted_bootstrap_randomforest.egg-info/SOURCES.txt
weighted_bootstrap_randomforest.egg-info/dependency_links.txt
weighted_bootstrap_randomforest.egg-info/requires.txt
weighted_bootstrap_randomforest.egg-info/top_level.txt